sequential_ft_transformer/__init__.py
sequential_ft_transformer/embeddings.py
sequential_ft_transformer/fttransformer.py
sequential_ft_transformer/plotting.py
sequential_ft_transformer/preprocessing.py
sequential_ft_transformer/transformer.py
sequential_ft_transformer-0.4.0.dist-info/LICENSE
sequential_ft_transformer-0.4.0.dist-info/METADATA
sequential_ft_transformer-0.4.0.dist-info/WHEEL
sequential_ft_transformer-0.4.0.dist-info/RECORD
