Metadata-Version: 2.1
Name: sequential_ft_transformer
Version: 0.4.0
Summary: FT Transformer applied to sequential tabular data
License: MIT
Author: Christian Orr
Requires-Python: >=3.10,<3.12
Classifier: License :: OSI Approved :: MIT License
Classifier: Programming Language :: Python :: 3
Classifier: Programming Language :: Python :: 3.10
Classifier: Programming Language :: Python :: 3.11
Requires-Dist: jax (==0.4.33)
Requires-Dist: jupyter (>=1.1.1,<2.0.0)
Requires-Dist: keras (>=3.5.0,<4.0.0)
Requires-Dist: matplotlib (>=3.9.2,<4.0.0)
Requires-Dist: pandas (>=2.2.3,<3.0.0)
Requires-Dist: pyarrow (>=17.0.0,<18.0.0)
Requires-Dist: scikit-learn (>=1.5.2,<2.0.0)
Requires-Dist: tensorflow (>=2.17.0,<3.0.0)
